kombu_fernet/__init__.py
kombu_fernet/serializers/__init__.py
kombu_fernet/serializers/json.py
kombu_fernet/serializers/msgpack.py
kombu_fernet/serializers/pickle.py
kombu_fernet/serializers/yaml.py
kombu_fernet_serializers-0.2.0.dist-info/LICENSE
kombu_fernet_serializers-0.2.0.dist-info/METADATA
kombu_fernet_serializers-0.2.0.dist-info/WHEEL
kombu_fernet_serializers-0.2.0.dist-info/entry_points.txt
kombu_fernet_serializers-0.2.0.dist-info/top_level.txt
kombu_fernet_serializers-0.2.0.dist-info/RECORD
