Metadata-Version: 2.1
Name: kombu-fernet-serializers
Version: 0.2.0
Summary: Symmetrically encrypted serializers for Kombu
Home-page: https://github.com/heroku/kombu-fernet-serializers
Author: David Gouldin
Author-email: dgouldin@heroku.com
License: MIT
Platform: UNKNOWN
Classifier: Development Status :: 5 - Production/Stable
Classifier: Intended Audience :: Developers
Classifier: Natural Language :: English
Classifier: License :: OSI Approved :: MIT License
Classifier: Programming Language :: Python
Classifier: Programming Language :: Python :: 2.7
Classifier: Programming Language :: Python :: 3.4
Classifier: Programming Language :: Python :: 3.5
Classifier: Programming Language :: Python :: 3.6
License-File: LICENSE
Requires-Dist: kombu (>=4.0.0)
Requires-Dist: cryptography (>=2.0.2)
Requires-Dist: six (>=1.10.0)
